[
    {
        "title": "My Robotics Journey",
        "slug": "robotics",
        "date": "2025-04-06T14:05:53-07:00",
        "tags": ["school", "robotics", "v5rc", "programming"],
        "contentFile": "en/portfolio/robotics.html",
        "lang": "en"
    },
    {
        "title": "Meine Robotik Reise",
        "slug": "robotik",
        "date": "2025-04-06T14:05:53-07:00",
        "tags": ["schule", "robotik", "v5rc", "programmierung"],
        "contentFile": "de/portfolio/robotik.html",
        "lang": "de"
    }
]